README.rst
setup.py
dictree/__init__.py
dictree/base.py
dictree/dictree.py
dictree/labels.py
dictree.egg-info/PKG-INFO
dictree.egg-info/SOURCES.txt
dictree.egg-info/dependency_links.txt
dictree.egg-info/top_level.txt