Metadata-Version: 1.1
Name: dictree
Version: 1.1.0
Summary: Tree structure with dict interface and wildcard feature
Home-page: http://github.com/tomokinakamaru/dictree
Author: Tomoki Nakamaru
Author-email: tomoki.nakamaru@gmail.com
License: MIT
Platform: any
Classifier: Development Status :: 4 - Beta
Classifier: Intended Audience :: Developers
Classifier: License :: OSI Approved :: MIT License
Classifier: Programming Language :: Python
Classifier: Topic :: Software Development :: Libraries :: Python Modules
